MANIFEST.in
README.md
requirements.txt
setup.py
keras_lr_multiplier/__init__.py
keras_lr_multiplier/backend.py
keras_lr_multiplier/multiplier.py
keras_lr_multiplier.egg-info/PKG-INFO
keras_lr_multiplier.egg-info/SOURCES.txt
keras_lr_multiplier.egg-info/dependency_links.txt
keras_lr_multiplier.egg-info/requires.txt
keras_lr_multiplier.egg-info/top_level.txt
tests/__init__.py
tests/test_multiplier.py