Metadata-Version: 2.1
Name: keras-lr-multiplier
Version: 0.9.0
Summary: Learning rate multiplier
Home-page: https://github.com/CyberZHG/keras-lr-multiplier
Author: CyberZHG
Author-email: CyberZHG@users.noreply.github.com
License: MIT
Platform: UNKNOWN
Classifier: Programming Language :: Python :: 2.7
Classifier: Programming Language :: Python :: 3.6
Classifier: Operating System :: OS Independent
